{
  "id": "elite-ghost-roaster",
  "name": "Elite Ghost Roaster",
  "species": "Ghoul",
  "gender": "Male",
  "element": "Undead",
  "primary_game": "Skylanders: SuperChargers",
  "appearances": [
    "Skylanders: SuperChargers (Racing)",
    "Skylanders: Imaginators"
  ],
  "cameos": null,
  "world": [],
  "quote": null,
  "description": null,
  "biography": null,
  "personality": null,
  "story": null,
  "wiki_url": "https://skylanders.fandom.com/wiki/Elite_Ghost_Roaster",
  "variants": [
    {
      "id": "elite-ghost-roaster",
      "variant_name": "Elite Ghost Roaster",
      "edition": "Series 1",
      "type": "SuperCharger",
      "game": "Skylanders: SuperChargers",
      "image": "https://static.wikia.nocookie.net/skylanders/images/f/f6/Eon%27s_Elite_Ghost_Roaster.jpg/revision/latest?cb=20170729040954",
      "attacks": [
        "Chain Whip",
        "Skull Charge",
        "Ectoplasm Mode",
        "Haunt",
        "Nightmare Touch"
      ],
      "stats": null,
      "wiki_url": "https://skylanders.fandom.com/wiki/Elite_Ghost_Roaster"
    }
  ]
}